amfiprot_amfitrack/__init__.py
amfiprot_amfitrack/device.py
amfiprot_amfitrack/payload.py
amfiprot_amfitrack-0.0.1a15.dist-info/licenses/LICENSE
amfiprot_amfitrack-0.0.1a15.dist-info/METADATA
amfiprot_amfitrack-0.0.1a15.dist-info/WHEEL
amfiprot_amfitrack-0.0.1a15.dist-info/top_level.txt
amfiprot_amfitrack-0.0.1a15.dist-info/RECORD
