Metadata-Version: 2.4
Name: amfiprot_amfitrack
Version: 0.0.1a15
Summary: AmfiTrack extension for Amfiprot
Author: Kristian Klein-Wengel
Author-email: kkw@amfitech.dk
Classifier: Programming Language :: Python :: 3
Classifier: License :: OSI Approved :: MIT License
Classifier: Operating System :: Microsoft :: Windows :: Windows 10
Requires-Python: >=3.6
License-File: LICENSE
Requires-Dist: amfiprot
Dynamic: license-file
